data_harvest_reader/__init__.py
data_harvest_reader/data_reader.py
data_harvest_reader-0.0.11.dist-info/LICENSE
data_harvest_reader-0.0.11.dist-info/METADATA
data_harvest_reader-0.0.11.dist-info/WHEEL
data_harvest_reader-0.0.11.dist-info/top_level.txt
data_harvest_reader-0.0.11.dist-info/RECORD
