Metadata-Version: 2.1
Name: data-harvest-reader
Version: 0.0.11
Summary: A class to handle and process multiple files with identical structures within a directory.
Home-page: https://github.com/Jeferson-Peter/data-harvest-reader
Author: Jeferson-Peter (Jeferson Peter)
Author-email: jeferson.peter@pm.me
Keywords: Python,File Reading,Multiple File Handler
Classifier: Development Status :: 1 - Planning
Classifier: Intended Audience :: Developers
Classifier: Programming Language :: Python :: 3.10
Classifier: Programming Language :: Python :: 3.11
Classifier: Programming Language :: Python :: 3.12
Classifier: Operating System :: Unix
Classifier: Operating System :: MacOS :: MacOS X
Classifier: Operating System :: Microsoft :: Windows
License-File: LICENSE
Requires-Dist: polars
Requires-Dist: loguru
Requires-Dist: colorama
